.coveragerc
.gitignore
README.rst
pkgmeta.cfg
setup.py
docs/Makefile
docs/changes.rst
docs/conf.py
docs/config.rst
docs/example.rst
docs/index.rst
docs/install.rst
docs/make.bat
docs/tests.rst
example/README
example/example.cfg.in
example/make.py
pkgmeta/__init__.py
pkgmeta/cli.py
pkgmeta/config.py
pkgmeta/exceptions.py
pkgmeta/indirection.py
pkgmeta/metadata.py
pkgmeta/releases.py
pkgmeta/repository.py
pkgmeta/storage.py
pkgmeta.egg-info/PKG-INFO
pkgmeta.egg-info/SOURCES.txt
pkgmeta.egg-info/dependency_links.txt
pkgmeta.egg-info/entry_points.txt
pkgmeta.egg-info/not-zip-safe
pkgmeta.egg-info/requires.txt
pkgmeta.egg-info/top_level.txt
pkgmeta/_compat/__init__.py
pkgmeta/_compat/packaging/__init__.py
pkgmeta/_compat/packaging/errors.py
pkgmeta/_compat/packaging/markers.py
pkgmeta/_compat/packaging/metadata.py
pkgmeta/_compat/packaging/version.py
pkgmeta/tests/__init__.py
pkgmeta/tests/base.py
pkgmeta/tests/mock_metadata.py
pkgmeta/tests/test_cli.py
pkgmeta/tests/test_config.py
pkgmeta/tests/test_metadata.py
pkgmeta/tests/test_releases.py
pkgmeta/tests/test_repository.py
pkgmeta/tests/test_storage.py
pkgmeta/tests/utils.py