Metadata-Version: 1.0
Name: pkgmeta
Version: 1.0a1
Summary: Python distribution metadata repository
Home-page: https://github.com/pumazi/pkgmeta
Author: Michael Mulich
Author-email: michael.mulich@gmail.com
License: GPL
Platform: UNKNOWN
Classifier: Programming Language :: Python
Classifier: Intended Audience :: Developers
Classifier: Development Status :: 3 - Alpha
